[
    {
        "type": "metadata",
        "timestamp": "2025-10-24 14:30:01",
        "speaker": "艾莉娅",
        "content": [],
        "processed": true
    },
    {
        "type": "metadata",
        "timestamp": "2025-10-24 14:30:05",
        "speaker": "艾莉娅",
        "content": [],
        "processed": true
    },
    {
        "type": "metadata",
        "timestamp": "2025-10-24 14:30:05",
        "speaker": "DiceBot",
        "content": [],
        "processed": true
    },
    {
        "type": "metadata",
        "timestamp": "2025-10-24 14:30:15",
        "speaker": "DM",
        "content": [],
        "processed": true
    },
    {
        "type": "metadata",
        "timestamp": "2025-10-24 14:30:30",
        "speaker": "艾莉娅",
        "content": [],
        "processed": true
    },
    {
        "type": "metadata",
        "timestamp": "2025-10-24 14:30:35",
        "speaker": "艾莉娅",
        "content": [],
        "processed": true
    },
    {
        "type": "metadata",
        "timestamp": "2025-10-24 14:30:35",
        "speaker": "DiceBot",
        "content": [],
        "processed": true
    },
    {
        "type": "metadata",
        "timestamp": "2025-10-24 14:30:45",
        "speaker": "DM",
        "content": [],
        "processed": true
    },
    {
        "type": "metadata",
        "timestamp": "2025-10-24 14:31:00",
        "speaker": "索恩",
        "content": [],
        "processed": true
    },
    {
        "type": "metadata",
        "timestamp": "2025-10-24 14:31:10",
        "speaker": "DM",
        "content": [],
        "processed": true
    },
    {
        "type": "metadata",
        "timestamp": "2025-10-24 14:31:25",
        "speaker": "索恩",
        "content": [],
        "processed": true
    },
    {
        "type": "metadata",
        "timestamp": "2025-10-24 14:31:30",
        "speaker": "艾莉娅",
        "content": [],
        "processed": true
    },
    {
        "type": "metadata",
        "timestamp": "2025-10-24 14:31:45",
        "speaker": "莉莉安",
        "content": [],
        "processed": true
    },
    {
        "type": "metadata",
        "timestamp": "2025-10-24 14:31:50",
        "speaker": "DM",
        "content": [],
        "processed": true
    },
    {
        "type": "metadata",
        "timestamp": "2025-10-24 14:31:55",
        "speaker": "莉莉安",
        "content": [],
        "processed": true
    },
    {
        "type": "metadata",
        "timestamp": "2025-10-24 14:31:55",
        "speaker": "DiceBot",
        "content": [],
        "processed": true
    },
    {
        "type": "metadata",
        "timestamp": "2025-10-24 14:32:10",
        "speaker": "DM",
        "content": [],
        "processed": true
    }
]